rggrader/__init__.py
rggrader/student.py
rggrader/submitter.py
rggrader-0.1.6.dist-info/METADATA
rggrader-0.1.6.dist-info/WHEEL
rggrader-0.1.6.dist-info/top_level.txt
rggrader-0.1.6.dist-info/RECORD
