Metadata-Version: 2.1
Name: rggrader
Version: 0.1.6
Summary: Submission tool for REA course
Author: Aditira Jamhuri
Author-email: aditira.jamhuri@ruangguru.com
Classifier: Programming Language :: Python
Classifier: Programming Language :: Python :: 3
Classifier: Programming Language :: Python :: 3.6
Classifier: Programming Language :: Python :: 3.7
Classifier: Programming Language :: Python :: 3.8
Requires-Dist: requests
Requires-Dist: pandas
Requires-Dist: Pillow
